savi/__init__.py
savi/binaria.py
savi/burbuja.py
savi/seleccion.py
savi-0.0.5.dist-info/LICENSE
savi-0.0.5.dist-info/METADATA
savi-0.0.5.dist-info/WHEEL
savi-0.0.5.dist-info/entry_points.txt
savi-0.0.5.dist-info/top_level.txt
savi-0.0.5.dist-info/RECORD
